vitrage_tempest_tests/README.rst
vitrage_tempest_tests/__init__.py
vitrage_tempest_tests/config.py
vitrage_tempest_tests/plugin.py
vitrage_tempest_tests/services/__init__.py
vitrage_tempest_tests/tests/__init__.py
vitrage_tempest_tests/tests/base.py
vitrage_tempest_tests/tests/utils.py
vitrage_tempest_tests/tests/api/__init__.py
vitrage_tempest_tests/tests/api/alarms/__init__.py
vitrage_tempest_tests/tests/api/alarms/base.py
vitrage_tempest_tests/tests/api/alarms/test_alarms.py
vitrage_tempest_tests/tests/api/event/__init__.py
vitrage_tempest_tests/tests/api/event/base.py
vitrage_tempest_tests/tests/api/event/test_events.py
vitrage_tempest_tests/tests/api/rca/__init__.py
vitrage_tempest_tests/tests/api/rca/base.py
vitrage_tempest_tests/tests/api/rca/test_rca.py
vitrage_tempest_tests/tests/api/resources/__init__.py
vitrage_tempest_tests/tests/api/resources/test_resources.py
vitrage_tempest_tests/tests/api/templates/__init__.py
vitrage_tempest_tests/tests/api/templates/base.py
vitrage_tempest_tests/tests/api/templates/test_template.py
vitrage_tempest_tests/tests/api/templates/test_template_v2.py
vitrage_tempest_tests/tests/api/topology/__init__.py
vitrage_tempest_tests/tests/api/topology/base.py
vitrage_tempest_tests/tests/api/topology/test_topology.py
vitrage_tempest_tests/tests/api/webhook/__init__.py
vitrage_tempest_tests/tests/api/webhook/test_webhook.py
vitrage_tempest_tests/tests/common/__init__.py
vitrage_tempest_tests/tests/common/aodh_utils.py
vitrage_tempest_tests/tests/common/ceilometer_utils.py
vitrage_tempest_tests/tests/common/cinder_utils.py
vitrage_tempest_tests/tests/common/constants.py
vitrage_tempest_tests/tests/common/general_utils.py
vitrage_tempest_tests/tests/common/glance_utils.py
vitrage_tempest_tests/tests/common/heat_utils.py
vitrage_tempest_tests/tests/common/neutron_utils.py
vitrage_tempest_tests/tests/common/nova_utils.py
vitrage_tempest_tests/tests/common/tempest_clients.py
vitrage_tempest_tests-0.0.1.dev237.dist-info/DESCRIPTION.rst
vitrage_tempest_tests-0.0.1.dev237.dist-info/METADATA
vitrage_tempest_tests-0.0.1.dev237.dist-info/RECORD
vitrage_tempest_tests-0.0.1.dev237.dist-info/WHEEL
vitrage_tempest_tests-0.0.1.dev237.dist-info/entry_points.txt
vitrage_tempest_tests-0.0.1.dev237.dist-info/metadata.json
vitrage_tempest_tests-0.0.1.dev237.dist-info/pbr.json
vitrage_tempest_tests-0.0.1.dev237.dist-info/top_level.txt
