Metadata-Version: 2.0
Name: vitrage-tempest-tests
Version: 0.0.1.dev237
Summary: Tempest plugin for Vitrage project
Home-page: http://www.openstack.org/
Author: OpenStack
Author-email: openstack-dev@lists.openstack.org
License: UNKNOWN
Platform: UNKNOWN
Classifier: Environment :: OpenStack
Classifier: Intended Audience :: Information Technology
Classifier: Intended Audience :: System Administrators
Classifier: License :: OSI Approved :: Apache Software License
Classifier: Operating System :: POSIX :: Linux
Classifier: Programming Language :: Python
Classifier: Programming Language :: Python :: 2
Classifier: Programming Language :: Python :: 2.7
Classifier: Programming Language :: Python :: 3
Classifier: Programming Language :: Python :: 3.3
Classifier: Programming Language :: Python :: 3.4
Requires-Dist: aodhclient (>=0.9.0)
Requires-Dist: networkx (>=1.10,<2.0)
Requires-Dist: oslo.config (>=5.1.0)
Requires-Dist: oslo.log (>=3.36.0)
Requires-Dist: oslo.serialization (!=2.19.1,>=2.18.0)
Requires-Dist: oslotest (>=3.2.0)
Requires-Dist: pbr (!=2.1.0,>=2.0.0)
Requires-Dist: python-ceilometerclient (>=2.5.0)
Requires-Dist: python-cinderclient (>=3.3.0)
Requires-Dist: python-dateutil (>=2.4.2)
Requires-Dist: python-glanceclient (>=2.8.0)
Requires-Dist: python-heatclient (>=1.10.0)
Requires-Dist: python-keystoneclient (>=3.8.0)
Requires-Dist: python-mistralclient (!=3.2.0,>=3.1.0)
Requires-Dist: python-neutronclient (>=6.7.0)
Requires-Dist: python-novaclient (>=9.1.0)
Requires-Dist: six (>=1.10.0)
Requires-Dist: tempest (>=17.1.0)
Requires-Dist: testtools (>=2.2.0)
